geopack/__init__.py
geopack/coordinates_vectorized.py
geopack/coordinates_vectorized_complex.py
geopack/geopack.py
geopack/igrf_vectorized.py
geopack/trace_field_lines_vectorized.py
geopack/trace_field_lines_vectorized_nointerp.py
geopack/igrf_coeffs/igrf10coeffs.txt
geopack/igrf_coeffs/igrf11coeffs.txt
geopack/igrf_coeffs/igrf12coeffs.txt
geopack/igrf_coeffs/igrf13coeffs.txt
geopack/igrf_coeffs/igrf14coeffs.txt
geopack/igrf_coeffs/igrf9coeffs.txt
geopack/models/__init__.py
geopack/models/t01.py
geopack/models/t04.py
geopack/models/t89.py
geopack/models/t96.py
geopack/vectorized/__init__.py
geopack/vectorized/condip1_exact_vectorized.py
geopack/vectorized/field_line_directional_derivatives_new.py
geopack/vectorized/field_line_geometry_vectorized.py
geopack/vectorized/t01_vectorized.py
geopack/vectorized/t04_vectorized.py
geopack/vectorized/t89_vectorized.py
geopack/vectorized/t96_vectorized.py
geopack_vectorized-1.1.4.dist-info/licenses/LICENSE
geopack_vectorized-1.1.4.dist-info/METADATA
geopack_vectorized-1.1.4.dist-info/WHEEL
geopack_vectorized-1.1.4.dist-info/top_level.txt
geopack_vectorized-1.1.4.dist-info/RECORD
