Metadata-Version: 2.4
Name: geopack-vectorized
Version: 1.1.4
Summary: Python implementation of geopack and Tsyganenko models with optimized vectorization
Home-page: https://github.com/Butadiene/geopack-vectorize
Author: geopack-vectorize contributors
Author-email: Sheng Tian <ts0110@atmos.ucla.edu>
Maintainer-email: Sheng Tian <ts0110@atmos.ucla.edu>
License: MIT
Project-URL: Homepage, https://github.com/Butadiene/geopack-vectorize
Project-URL: Documentation, https://github.com/Butadiene/geopack-vectorize#readme
Project-URL: Repository, https://github.com/Butadiene/geopack-vectorize
Project-URL: Issues, https://github.com/Butadiene/geopack-vectorize/issues
Keywords: geopack,space physics,Tsyganenko model,magnetosphere,geomagnetic field
Platform: any
Classifier: Development Status :: 4 - Beta
Classifier: Intended Audience :: Science/Research
Classifier: License :: OSI Approved :: MIT License
Classifier: Operating System :: OS Independent
Classifier: Programming Language :: Python :: 3
Classifier: Programming Language :: Python :: 3.7
Classifier: Programming Language :: Python :: 3.8
Classifier: Programming Language :: Python :: 3.9
Classifier: Programming Language :: Python :: 3.10
Classifier: Programming Language :: Python :: 3.11
Classifier: Topic :: Scientific/Engineering :: Physics
Classifier: Topic :: Scientific/Engineering :: Astronomy
Requires-Python: >=3.7
License-File: LICENSE
Requires-Dist: numpy>=1.16.0
Requires-Dist: scipy>=1.0.0
Provides-Extra: dev
Requires-Dist: pytest>=6.0; extra == "dev"
Requires-Dist: pytest-cov>=2.0; extra == "dev"
Requires-Dist: matplotlib>=3.0; extra == "dev"
Provides-Extra: examples
Requires-Dist: matplotlib>=3.0; extra == "examples"
Requires-Dist: jupyter>=1.0; extra == "examples"
Dynamic: author
Dynamic: home-page
Dynamic: license-file
Dynamic: platform
